docusense/__init__.py
docusense/keywords.py
docusense/process_doc.py
docusense/qa.py
docusense/sense.py
docusense/summary.py
docusense/utils.py
docusense-0.0.1.dist-info/LICENSE
docusense-0.0.1.dist-info/METADATA
docusense-0.0.1.dist-info/WHEEL
docusense-0.0.1.dist-info/RECORD
