Metadata-Version: 2.1
Name: docusense
Version: 0.0.1
Summary: A tool to extract logic from document
Home-page: https://github.com/GytisBaravykas/docusense
License: MIT
Keywords: nlp,text-mining,algorithms,development
Author: Gytis Baravykas
Requires-Python: >=3.8.0
Classifier: License :: OSI Approved :: MIT License
Classifier: Programming Language :: Python :: 3
Classifier: Programming Language :: Python :: 3.8
Classifier: Programming Language :: Python :: 3.9
Classifier: Programming Language :: Python :: 3.10
Classifier: Programming Language :: Python :: 3.11
Requires-Dist: argparse (>=1.4.0,<2.0.0)
Requires-Dist: docx2txt (>=0.8,<0.9)
Requires-Dist: nltk (>=3.8.1,<4.0.0)
Requires-Dist: protobuf (>=3.20.0,<3.21.0)
Requires-Dist: pypdf2 (>=3.0.1,<4.0.0)
Requires-Dist: scikit-learn (>=1.2.2,<2.0.0)
Requires-Dist: sentencepiece (>=0.1.99,<0.2.0)
Requires-Dist: torch (>=2.0.1,<3.0.0)
Requires-Dist: transformers (>=4.29.2,<5.0.0)
